{
    "training_episodes": 0,
    "((3, 2), (1, 1), 0)": {
        "stay": 0.0,
        "move_down": 0.0,
        "move_up": 0.0,
        "move_left": 0.0,
        "move_right": 0.0
    },
    "((3, 2), (0, 1), 0)": {
        "move_right": 0.0,
        "move_down": 0.0,
        "move_left": 0.0,
        "stay": 0.0
    },
    "((4, 2), (0, 2), 0)": {
        "move_down": 0.0,
        "move_up": 0.0,
        "move_left": 0.0,
        "stay": 0.0
    },
    "((4, 1), (0, 1), 0)": {
        "move_down": 0.0,
        "move_up": 0.0,
        "move_left": 0.0,
        "stay": 0.0
    },
    "((4, 0), (0, 2), 0)": {
        "stay": 0.0,
        "move_left": 0.0,
        "move_up": 0.0
    },
    "((3, 0), (0, 2), 0)": {
        "move_left": 0.0,
        "move_up": 0.0,
        "stay": 0.0,
        "move_right": 0.0
    },
    "((2, 0), (1, 2), 0)": {
        "move_right": 0.0,
        "move_up": 0.0,
        "move_left": 0.0
    },
    "((3, 0), (1, 3), 0)": {
        "move_up": 0.0,
        "stay": 0.0
    },
    "((3, 1), (1, 2), 0)": {
        "move_right": 0.0,
        "stay": 0.0,
        "move_up": 0.0
    },
    "((4, 1), (1, 3), 0)": {
        "move_left": 0.0,
        "move_up": 0.0,
        "move_down": 0.0
    },
    "((3, 1), (1, 3), 0)": {
        "stay": 0.0,
        "move_right": 0.0,
        "move_down": 0.0
    },
    "((3, 1), (0, 3), 0)": {
        "move_right": 0.0,
        "stay": 0.0,
        "move_down": 0.0,
        "move_left": 0.0
    },
    "((4, 1), (0, 2), 0)": {
        "move_left": 0.0,
        "move_up": 0.0,
        "move_down": 0.0
    },
    "((4, 1), (0, 3), 0)": {
        "move_up": 0.0,
        "move_down": 0.0
    },
    "((4, 3), (0, 3), 0)": {
        "stay": 0.0,
        "move_down": 0.0
    },
    "((4, 3), (1, 3), 0)": {
        "stay": 0.0,
        "move_left": 0.0
    },
    "((3, 3), (1, 3), 0)": {
        "move_right": 0.0,
        "move_down": 0.0,
        "move_left": 0.0
    },
    "((3, 1), (0, 2), 0)": {
        "move_down": 0.0,
        "move_right": 0.0,
        "move_up": 0.0,
        "stay": 0.0,
        "move_left": 0.0
    },
    "((3, 0), (0, 1), 0)": {
        "move_right": 0.0,
        "stay": 0.0
    },
    "((4, 0), (0, 0), 0)": {
        "stay": 0.0,
        "move_up": 0.0
    },
    "((4, 0), (0, 1), 0)": {
        "move_up": 0.0,
        "stay": 0.0
    },
    "((4, 1), (1, 1), 0)": {
        "move_left": 0.0,
        "stay": 0.0
    },
    "((3, 1), (1, 0), 0)": {
        "move_right": 0.0,
        "move_left": 0.0,
        "stay": 0.0,
        "move_down": 0.0,
        "move_up": 0.0
    },
    "((4, 1), (0, 0), 0)": {
        "move_down": 0.0,
        "move_up": 0.0
    },
    "((3, 2), (0, 3), 0)": {
        "move_down": 0.0,
        "stay": 0.0
    },
    "((4, 1), (1, 2), 0)": {
        "move_up": 0.0,
        "move_left": 0.0,
        "stay": 0.0,
        "move_down": 0.0
    },
    "((4, 2), (2, 2), 0)": {
        "move_left": 0.0,
        "move_down": 0.0
    },
    "((3, 2), (2, 3), 0)": {
        "move_up": 0.0,
        "move_right": 0.0,
        "move_down": 0.0
    },
    "((3, 2), (3, 3), 1)": {
        "stay": 0.0,
        "move_right": 0.0
    },
    "((3, 2), (4, 3), 1)": {
        "move_down": 0.0
    },
    "((3, 1), (4, 2), 1)": {
        "move_right": 0.0,
        "stay": 0.0,
        "move_up": 0.0,
        "move_left": 0.0
    },
    "((2, 2), (0, 2), 0)": {
        "stay": 0.0,
        "move_left": 0.0,
        "move_right": 0.0,
        "move_up": 0.0
    },
    "((1, 2), (0, 2), 0)": {
        "move_right": 0.0,
        "move_down": 0.0,
        "move_up": 0.0,
        "stay": 0.0008100000000000002
    },
    "((2, 2), (0, 1), 0)": {
        "move_down": 0.0,
        "move_up": 0.0,
        "stay": 0.0,
        "move_right": 0.0
    },
    "((2, 1), (0, 2), 0)": {
        "move_up": 0.0,
        "move_right": 0.0,
        "move_left": 0.0
    },
    "((2, 2), (0, 3), 0)": {
        "move_down": 0.0,
        "move_right": 0.0
    },
    "((2, 2), (1, 2), 0)": {
        "move_down": 0.0,
        "move_left": 0.0
    },
    "((2, 1), (1, 3), 0)": {
        "move_down": 0.0,
        "move_up": 0.0,
        "move_right": 0.0
    },
    "((2, 0), (2, 3), 0)": {
        "move_up": 0.0,
        "stay": 0.0
    },
    "((2, 2), (2, 3), 0)": {
        "stay": 0.0,
        "move_right": 0.0,
        "move_down": 0.0,
        "move_left": 0.0
    },
    "((4, 2), (3, 3), 0)": {
        "move_down": 0.0,
        "stay": 0.0
    },
    "((4, 1), (4, 3), 0)": {
        "move_up": 0.0
    },
    "((4, 1), (4, 2), 1)": {
        "move_up": 0.0
    },
    "((3, 2), (1, 1), 1)": {
        "move_down": 0.0,
        "move_left": 0.0,
        "move_right": 0.0,
        "stay": 0.0,
        "move_up": 0.0
    },
    "((3, 1), (2, 1), 1)": {
        "stay": 0.0,
        "move_down": 0.0
    },
    "((3, 1), (2, 2), 1)": {
        "stay": 0.0
    },
    "((3, 1), (3, 2), 1)": {
        "move_left": 0.0,
        "stay": 0.0
    },
    "((2, 1), (4, 2), 1)": {
        "move_down": 0.0
    },
    "((3, 1), (2, 2), 0)": {
        "move_down": 0.0,
        "move_left": 0.0
    },
    "((3, 0), (2, 2), 0)": {
        "move_left": 0.0
    },
    "((2, 0), (2, 2), 0)": {
        "stay": 0.0,
        "move_left": 0.0
    },
    "((1, 0), (2, 2), 0)": {
        "move_left": 0.0
    },
    "((0, 0), (2, 2), 0)": {
        "move_right": 0.0,
        "stay": 0.0
    },
    "((1, 0), (2, 1), 0)": {
        "move_right": 0.0,
        "move_left": 0.0
    },
    "((1, 0), (2, 0), 1)": {
        "stay": 0.0
    },
    "((1, 0), (2, 1), 1)": {
        "move_right": 0.0,
        "move_up": 0.0
    },
    "((2, 0), (3, 1), 1)": {
        "stay": 0.0
    },
    "((2, 0), (4, 1), 1)": {
        "move_up": 0.0
    },
    "((3, 2), (1, 0), 0)": {
        "move_down": 0.0,
        "move_left": 0.0,
        "move_right": 0.0,
        "stay": 0.0
    },
    "((2, 1), (0, 0), 0)": {
        "stay": 0.0,
        "move_down": 0.0
    },
    "((2, 1), (1, 0), 0)": {
        "stay": 0.0,
        "move_right": 0.0,
        "move_left": 0.0,
        "move_down": 0.0
    },
    "((3, 1), (0, 0), 0)": {
        "move_up": 0.0,
        "move_left": 0.0
    },
    "((3, 2), (0, 2), 0)": {
        "move_up": 0.0,
        "move_right": 0.0,
        "stay": 0.0,
        "move_down": 0.0,
        "move_left": 0.0
    },
    "((3, 3), (0, 3), 0)": {
        "move_down": 0.0
    },
    "((4, 2), (1, 3), 0)": {
        "move_left": 0.0,
        "stay": 0.0,
        "move_down": 0.0,
        "move_up": 0.0
    },
    "((3, 2), (1, 2), 0)": {
        "move_up": 0.0,
        "move_right": 0.0
    },
    "((3, 3), (0, 2), 0)": {
        "move_right": 0.0,
        "move_left": 0.0
    },
    "((4, 2), (1, 2), 0)": {
        "stay": 0.0,
        "move_up": 0.0,
        "move_left": 0.0,
        "move_down": 0.0
    },
    "((4, 1), (2, 3), 0)": {
        "stay": 0.0,
        "move_up": 0.0
    },
    "((4, 1), (3, 3), 0)": {
        "move_down": 0.0,
        "move_left": 0.0
    },
    "((4, 0), (4, 3), 0)": {
        "stay": 0.0
    },
    "((4, 0), (4, 2), 0)": {
        "move_left": 0.0,
        "move_up": 0.0,
        "stay": 0.0
    },
    "((3, 0), (3, 2), 0)": {
        "move_right": 0.0,
        "stay": 0.0,
        "move_up": 0.0,
        "move_left": 0.0
    },
    "((4, 0), (3, 2), 0)": {
        "move_up": 0.0,
        "stay": 0.0,
        "move_left": 0.0
    },
    "((4, 1), (3, 2), 0)": {
        "move_up": 0.0,
        "move_left": 0.0,
        "stay": 0.0,
        "move_down": 0.0
    },
    "((4, 2), (3, 2), 0)": {
        "move_down": 0.0,
        "move_left": 0.0,
        "move_up": 0.0
    },
    "((4, 1), (2, 2), 0)": {
        "move_up": 0.0,
        "stay": 0.0,
        "move_left": 0.0
    },
    "((4, 2), (2, 3), 0)": {
        "stay": 0.0,
        "move_down": 0.0
    },
    "((3, 1), (4, 3), 0)": {
        "move_down": 0.0
    },
    "((3, 0), (3, 3), 0)": {
        "stay": 0.0,
        "move_left": 0.0
    },
    "((3, 0), (4, 3), 0)": {
        "move_up": 0.0
    },
    "((3, 1), (3, 3), 0)": {
        "move_left": 0.0,
        "stay": 0.0,
        "move_right": 0.0
    },
    "((2, 1), (3, 2), 0)": {
        "move_right": 0.0,
        "move_left": 0.0,
        "move_up": 0.0,
        "stay": 0.0,
        "move_down": 0.0
    },
    "((3, 1), (3, 2), 0)": {
        "move_down": 0.0,
        "move_right": 0.0,
        "move_left": 0.0,
        "stay": 0.0,
        "move_up": 0.0
    },
    "((3, 0), (4, 2), 0)": {
        "move_up": 0.0,
        "move_right": 0.0,
        "stay": 0.0,
        "move_left": 0.0
    },
    "((4, 1), (4, 2), 0)": {
        "move_down": 0.0,
        "stay": 0.0,
        "move_left": 0.0
    },
    "((2, 1), (4, 2), 0)": {
        "move_up": 0.0,
        "move_right": 0.0,
        "move_down": 0.0,
        "move_left": 0.0
    },
    "((2, 2), (3, 2), 0)": {
        "stay": 0.0,
        "move_down": 0.0
    },
    "((2, 2), (3, 3), 0)": {
        "move_left": 0.0
    },
    "((1, 2), (3, 2), 0)": {
        "move_down": 0.0,
        "move_right": 0.0,
        "move_up": 0.0
    },
    "((1, 1), (2, 2), 0)": {
        "move_right": 0.0
    },
    "((2, 1), (2, 2), 0)": {
        "move_right": 0.0,
        "move_down": 0.0
    },
    "((2, 1), (1, 2), 0)": {
        "move_right": 0.0,
        "move_left": 0.0,
        "move_down": 0.0,
        "move_up": 0.0
    },
    "((3, 0), (0, 3), 0)": {
        "move_up": 0.0
    },
    "((1, 1), (1, 2), 0)": {
        "move_down": 0.0,
        "move_up": 0.0,
        "stay": 0.0,
        "move_right": 0.0
    },
    "((1, 0), (1, 2), 0)": {
        "move_up": 0.0,
        "stay": 0.0,
        "move_left": 0.0
    },
    "((1, 1), (1, 3), 0)": {
        "stay": 0.0,
        "move_up": 0.0,
        "move_right": 0.0
    },
    "((1, 2), (1, 3), 0)": {
        "move_left": 0.0,
        "move_up": 0.0,
        "move_right": 0.0
    },
    "((0, 2), (0, 3), 0)": {
        "move_up": 0.0,
        "move_down": 0.0,
        "move_right": 0.0
    },
    "((0, 1), (0, 3), 0)": {
        "stay": 0.0
    },
    "((0, 1), (0, 2), 0)": {
        "move_right": 0.0,
        "move_down": 0.0
    },
    "((1, 1), (0, 3), 0)": {
        "move_left": 0.0
    },
    "((0, 1), (1, 3), 0)": {
        "move_right": 0.0,
        "stay": 0.0,
        "move_up": 0.0
    },
    "((2, 0), (1, 3), 0)": {
        "stay": 0.0,
        "move_left": 0.0
    },
    "((3, 1), (2, 3), 0)": {
        "move_left": 0.0,
        "stay": 0.0
    },
    "((2, 1), (3, 3), 0)": {
        "stay": 0.0
    },
    "((2, 1), (4, 3), 0)": {
        "move_left": 0.0
    },
    "((1, 1), (4, 2), 0)": {
        "stay": 0.0,
        "move_up": 0.0,
        "move_left": 0.0
    },
    "((1, 2), (4, 2), 0)": {
        "move_down": 0.0
    },
    "((1, 1), (4, 1), 0)": {
        "move_down": 0.0
    },
    "((1, 0), (3, 1), 0)": {
        "move_up": 0.0
    },
    "((1, 1), (3, 1), 0)": {
        "stay": 0.0
    },
    "((1, 1), (2, 1), 0)": {
        "move_right": 0.0
    },
    "((2, 1), (3, 1), 0)": {
        "move_down": 0.0
    },
    "((2, 0), (3, 2), 0)": {
        "stay": 0.0,
        "move_up": 0.0,
        "move_right": 0.0
    },
    "((2, 0), (4, 2), 0)": {
        "move_left": 0.0,
        "stay": 0.0,
        "move_right": 0.0,
        "move_up": 0.0
    },
    "((1, 0), (4, 2), 0)": {
        "stay": 0.0
    },
    "((1, 0), (4, 3), 0)": {
        "stay": 0.0
    },
    "((1, 0), (3, 3), 0)": {
        "stay": 0.0,
        "move_up": 0.0
    },
    "((1, 1), (3, 3), 0)": {
        "move_up": 0.0
    },
    "((1, 2), (2, 2), 1)": {
        "move_up": 0.0
    },
    "((1, 3), (3, 2), 1)": {
        "stay": 0.0,
        "move_right": 0.0
    },
    "((1, 3), (4, 2), 1)": {
        "move_down": 0.0
    },
    "((2, 2), (2, 1), 1)": {
        "move_up": 0.0,
        "move_down": 0.0,
        "move_left": 0.0
    },
    "((2, 3), (3, 1), 1)": {
        "stay": 0.0,
        "move_down": 0.0
    },
    "((2, 3), (4, 1), 1)": {
        "move_left": 0.0,
        "move_right": 0.0,
        "stay": 0.0
    },
    "((4, 2), (2, 1), 1)": {
        "move_down": 0.0,
        "stay": 0.0,
        "move_up": 0.0
    },
    "((4, 1), (3, 1), 1)": {
        "move_up": 0.0,
        "move_left": 0.0,
        "stay": 0.0
    },
    "((4, 2), (3, 1), 1)": {
        "move_down": 0.0,
        "stay": 0.0
    },
    "((4, 1), (3, 1), 0)": {
        "stay": 0.0,
        "move_up": 0.0,
        "move_left": 0.0
    },
    "((4, 1), (3, 0), 0)": {
        "stay": 0.0,
        "move_left": 0.0,
        "move_down": 0.0
    },
    "((4, 1), (4, 0), 0)": {
        "move_up": 0.0
    },
    "((4, 2), (4, 0), 0)": {
        "move_left": 0.0,
        "move_down": 0.0
    },
    "((3, 2), (4, 1), 0)": {
        "move_down": 0.0
    },
    "((3, 1), (4, 2), 0)": {
        "move_left": 0.0,
        "move_down": 0.0,
        "move_up": 0.0,
        "move_right": 0.0
    },
    "((1, 1), (3, 2), 0)": {
        "move_left": 0.0,
        "stay": 0.0
    },
    "((0, 1), (4, 2), 0)": {
        "move_down": 0.0,
        "move_left": 0.1
    },
    "((0, 0), (4, 1), 0)": {
        "move_right": 0.0
    },
    "((1, 0), (4, 0), 0)": {
        "move_right": 0.0
    },
    "((2, 0), (4, 1), 0)": {
        "move_right": 0.0
    },
    "((3, 0), (3, 1), 0)": {
        "move_left": 0.0,
        "move_right": 0.0,
        "move_up": 0.0
    },
    "((2, 0), (3, 1), 0)": {
        "move_left": 0.0
    },
    "((1, 0), (3, 0), 0)": {
        "move_left": 0.0
    },
    "((0, 0), (2, 0), 0)": {
        "move_up": 0.0,
        "stay": 0.0
    },
    "((0, 1), (1, 0), 0)": {
        "move_left": 0.19
    },
    "((3, 1), (0, 1), 0)": {
        "move_left": 0.0,
        "move_down": 0.0,
        "move_up": 0.0
    },
    "((2, 1), (1, 1), 0)": {
        "stay": 0.0
    },
    "((1, 1), (1, 2), 1)": {
        "move_left": 0.0,
        "move_down": 0.0
    },
    "((0, 1), (2, 2), 1)": {
        "stay": 0.0
    },
    "((0, 1), (3, 2), 1)": {
        "move_down": 0.0
    },
    "((0, 0), (4, 2), 1)": {
        "move_right": 0.0
    },
    "((3, 0), (1, 1), 0)": {
        "stay": 0.0,
        "move_right": 0.0,
        "move_left": 0.0
    },
    "((4, 0), (1, 1), 0)": {
        "stay": 0.0,
        "move_left": 0.0,
        "move_up": 0.0
    },
    "((4, 0), (1, 0), 0)": {
        "move_left": 0.0
    },
    "((3, 0), (0, 0), 0)": {
        "move_right": 0.0,
        "stay": 0.0,
        "move_left": 0.0
    },
    "((4, 3), (1, 2), 0)": {
        "move_left": 0.0,
        "move_down": 0.0
    },
    "((3, 2), (1, 3), 0)": {
        "move_right": 0.0,
        "stay": 0.0
    },
    "((3, 3), (1, 1), 0)": {
        "stay": 0.0
    },
    "((3, 3), (2, 1), 0)": {
        "move_down": 0.0
    },
    "((3, 2), (2, 2), 0)": {
        "stay": 0.0,
        "move_left": 0.0,
        "move_down": 0.0
    },
    "((3, 2), (2, 1), 0)": {
        "move_left": 0.0,
        "move_up": 0.0
    },
    "((2, 2), (2, 0), 0)": {
        "stay": 0.0,
        "move_right": 0.0
    },
    "((2, 2), (3, 0), 0)": {
        "move_down": 0.0,
        "stay": 0.0
    },
    "((2, 1), (2, 0), 0)": {
        "move_up": 0.0
    },
    "((3, 2), (3, 0), 0)": {
        "move_up": 0.0
    },
    "((3, 3), (4, 0), 0)": {
        "move_left": 0.0,
        "stay": 0.0
    },
    "((2, 3), (4, 1), 0)": {
        "stay": 0.0,
        "move_left": 0.0
    },
    "((1, 3), (4, 1), 0)": {
        "stay": 0.0,
        "move_left": 0.0
    },
    "((0, 3), (4, 1), 0)": {
        "move_right": 0.0
    },
    "((1, 3), (3, 1), 0)": {
        "move_down": 0.0
    },
    "((1, 2), (4, 1), 0)": {
        "move_right": 0.0,
        "move_up": 0.0
    },
    "((2, 2), (4, 2), 0)": {
        "move_right": 0.0
    },
    "((3, 2), (4, 2), 0)": {
        "stay": 0.0,
        "move_up": 0.0,
        "move_down": 0.0
    },
    "((3, 3), (4, 2), 0)": {
        "move_down": 0.0
    },
    "((3, 2), (4, 3), 0)": {
        "move_down": 0.0
    },
    "((4, 3), (2, 2), 0)": {
        "move_left": 0.0,
        "move_down": 0.0,
        "stay": 0.0
    },
    "((3, 3), (3, 2), 0)": {
        "move_left": 0.0,
        "stay": 0.0,
        "move_right": 0.0
    },
    "((2, 3), (3, 3), 0)": {
        "move_left": 0.0
    },
    "((1, 3), (3, 3), 0)": {
        "move_down": 0.0
    },
    "((1, 2), (2, 3), 0)": {
        "move_right": 0.0
    },
    "((0, 0), (2, 1), 0)": {
        "move_up": 0.0
    },
    "((0, 1), (2, 1), 0)": {
        "move_down": 0.0
    },
    "((0, 0), (1, 0), 0)": {
        "stay": 0.0
    },
    "((0, 0), (1, 1), 0)": {
        "stay": 0.0,
        "move_right": 0.0
    },
    "((1, 0), (1, 1), 0)": {
        "move_up": 0.0,
        "move_left": 0.0
    },
    "((1, 1), (0, 1), 0)": {
        "move_down": 0.0,
        "move_up": 0.0
    },
    "((1, 0), (0, 1), 0)": {
        "move_left": 0.0,
        "stay": 0.0,
        "move_up": 0.0
    },
    "((0, 0), (0, 1), 0)": {
        "move_right": 0.0,
        "move_up": 0.0
    },
    "((0, 0), (1, 1), 1)": {
        "move_up": 0.0
    },
    "((0, 1), (2, 1), 1)": {
        "move_down": 0.0
    },
    "((0, 0), (3, 1), 1)": {
        "stay": 0.0
    },
    "((0, 0), (4, 1), 1)": {
        "stay": 0.0
    },
    "((2, 2), (1, 0), 0)": {
        "stay": 0.0,
        "move_up": 0.0,
        "move_right": 0.0,
        "move_down": 0.0
    },
    "((2, 2), (0, 0), 0)": {
        "move_right": 0.0,
        "stay": 0.0
    },
    "((3, 3), (2, 2), 0)": {
        "move_right": 0.0
    },
    "((4, 3), (3, 2), 0)": {
        "move_left": 0.0,
        "move_down": 0.0,
        "stay": 0.0
    },
    "((4, 2), (4, 3), 0)": {
        "move_up": 0.0,
        "move_left": 0.0,
        "move_down": 0.0
    },
    "((4, 2), (4, 3), 1)": {
        "move_left": 0.0,
        "move_down": 0.0
    },
    "((4, 1), (3, 3), 1)": {
        "move_up": 0.0
    },
    "((4, 2), (3, 2), 1)": {
        "move_down": 0.0
    },
    "((4, 1), (3, 2), 1)": {
        "move_left": 0.0,
        "stay": 0.0
    },
    "((3, 3), (0, 1), 0)": {
        "move_down": 0.0,
        "move_right": 0.0,
        "move_left": 0.0
    },
    "((4, 2), (0, 1), 0)": {
        "move_left": 0.0,
        "move_down": 0.0,
        "stay": 0.0
    },
    "((2, 3), (0, 2), 0)": {
        "move_left": 0.0,
        "move_down": 0.0
    },
    "((1, 3), (0, 2), 0)": {
        "stay": 0.0,
        "move_left": 0.0
    },
    "((1, 3), (0, 3), 0)": {
        "move_left": 0.0,
        "stay": 0.0,
        "move_down": 0.0,
        "move_right": 0.0
    },
    "((1, 3), (0, 3), 1)": {
        "move_down": 0.0,
        "move_left": 0.0
    },
    "((1, 2), (0, 2), 1)": {
        "move_down": 0.0,
        "move_left": 0.0
    },
    "((1, 1), (0, 1), 1)": {
        "move_up": 0.0,
        "stay": 0.0
    },
    "((1, 0), (0, 0), 1)": {
        "move_right": 0.0
    },
    "((2, 0), (0, 1), 1)": {
        "move_left": 0.0
    },
    "((1, 0), (1, 1), 1)": {
        "stay": 0.0
    },
    "((1, 1), (3, 1), 1)": {
        "move_right": 0.0
    },
    "((2, 1), (4, 1), 1)": {
        "move_left": 0.0
    },
    "((1, 3), (0, 1), 0)": {
        "move_right": 0.0
    },
    "((2, 3), (0, 3), 0)": {
        "move_down": 0.0,
        "move_right": 0.0,
        "stay": 0.0
    },
    "((2, 2), (1, 3), 0)": {
        "stay": 0.0,
        "move_down": 0.0,
        "move_right": 0.0,
        "move_left": 0.0
    },
    "((1, 0), (1, 3), 0)": {
        "stay": 0.0,
        "move_right": 0.0
    },
    "((1, 0), (0, 3), 0)": {
        "move_up": 0.0,
        "stay": 0.0,
        "move_left": 0.0
    },
    "((1, 1), (0, 2), 0)": {
        "move_right": 0.0,
        "move_left": 0.0
    },
    "((2, 1), (0, 1), 0)": {
        "move_left": 0.0
    },
    "((1, 1), (0, 0), 0)": {
        "move_right": 0.0,
        "stay": 0.0,
        "move_left": 0.009000000000000001
    },
    "((1, 1), (1, 0), 0)": {
        "move_down": 0.0,
        "move_right": 0.0
    },
    "((1, 1), (1, 0), 1)": {
        "move_down": 0.0
    },
    "((1, 1), (0, 0), 1)": {
        "move_right": 0.0
    },
    "((2, 1), (1, 0), 1)": {
        "move_down": 0.0
    },
    "((2, 0), (1, 1), 1)": {
        "move_up": 0.0
    },
    "((1, 1), (0, 2), 1)": {
        "move_up": 0.0
    },
    "((1, 0), (2, 2), 1)": {
        "move_left": 0.0
    },
    "((0, 0), (3, 2), 1)": {
        "move_up": 0.0
    },
    "((0, 1), (4, 2), 1)": {
        "move_right": 0.0
    },
    "((4, 2), (3, 0), 0)": {
        "stay": 0.0,
        "move_down": 0.0
    },
    "((3, 1), (4, 0), 0)": {
        "stay": 0.0,
        "move_up": 0.0
    },
    "((3, 2), (4, 0), 0)": {
        "stay": 0.0,
        "move_up": 0.0,
        "move_right": 0.0
    },
    "((3, 3), (4, 1), 0)": {
        "move_down": 0.0
    },
    "((2, 2), (3, 1), 0)": {
        "move_left": 0.0,
        "move_down": 0.0
    },
    "((1, 3), (4, 2), 0)": {
        "stay": 0.0,
        "move_left": 0.0
    },
    "((0, 3), (4, 2), 0)": {
        "stay": 0.0
    },
    "((0, 3), (3, 2), 0)": {
        "move_down": 0.0
    },
    "((0, 2), (3, 1), 0)": {
        "move_left": 0.1
    },
    "((2, 1), (3, 1), 1)": {
        "move_right": 0.0
    },
    "((1, 2), (3, 1), 1)": {
        "move_down": 0.0,
        "stay": 0.0
    },
    "((1, 1), (4, 1), 1)": {
        "move_down": 0.0
    },
    "((4, 2), (1, 0), 0)": {
        "move_up": 0.0,
        "stay": 0.0
    },
    "((4, 3), (1, 1), 0)": {
        "move_left": 0.0,
        "move_down": 0.0
    },
    "((4, 3), (0, 2), 0)": {
        "stay": 0.0,
        "move_left": 0.0,
        "move_down": 0.0
    },
    "((4, 3), (0, 1), 0)": {
        "stay": 0.0
    },
    "((4, 3), (0, 0), 0)": {
        "move_left": 0.0,
        "stay": 0.0,
        "move_down": 0.0
    },
    "((3, 3), (0, 0), 0)": {
        "move_right": 0.0,
        "move_left": 0.0,
        "stay": 0.0,
        "move_down": 0.0
    },
    "((4, 3), (1, 0), 0)": {
        "move_left": 0.0
    },
    "((2, 3), (1, 0), 0)": {
        "move_right": 0.0
    },
    "((3, 3), (1, 0), 0)": {
        "move_down": 0.0,
        "move_right": 0.0,
        "stay": 0.0,
        "move_left": 0.0
    },
    "((3, 2), (0, 0), 0)": {
        "move_down": 0.0,
        "move_up": 0.0,
        "stay": 0.0
    },
    "((3, 3), (4, 3), 0)": {
        "move_right": 0.0
    },
    "((3, 3), (4, 3), 1)": {
        "move_right": 0.0
    },
    "((3, 3), (4, 2), 1)": {
        "stay": 0.0,
        "move_down": 0.0
    },
    "((3, 2), (2, 1), 1)": {
        "move_right": 0.0,
        "move_left": 0.0,
        "stay": 0.0,
        "move_down": 0.0
    },
    "((4, 2), (4, 1), 1)": {
        "move_down": 0.0,
        "move_left": 0.0,
        "stay": 0.0
    },
    "((3, 0), (2, 1), 1)": {
        "move_right": 0.0
    },
    "((4, 0), (3, 1), 1)": {
        "move_up": 0.0
    },
    "((4, 1), (3, 0), 1)": {
        "move_left": 0.0,
        "move_down": 0.0
    },
    "((3, 1), (2, 0), 1)": {
        "move_left": 0.0
    },
    "((2, 1), (3, 0), 1)": {
        "move_up": 0.0
    },
    "((2, 2), (3, 1), 1)": {
        "stay": 0.0,
        "move_up": 0.0,
        "move_left": 0.0
    },
    "((2, 2), (4, 1), 1)": {
        "move_down": 0.0,
        "move_left": 0.0,
        "stay": 0.0,
        "move_up": 0.0
    },
    "((2, 0), (1, 0), 0)": {
        "move_right": 0.0
    },
    "((3, 0), (1, 0), 0)": {
        "move_left": 0.0
    },
    "((2, 0), (0, 0), 0)": {
        "move_right": 0.0,
        "move_left": 0.0
    },
    "((3, 0), (1, 2), 0)": {
        "move_left": 0.0,
        "stay": 0.0,
        "move_up": 0.0
    },
    "((2, 0), (0, 3), 0)": {
        "move_left": 0.0
    },
    "((1, 0), (0, 2), 0)": {
        "move_right": 0.0
    },
    "((0, 0), (1, 3), 0)": {
        "move_right": 0.0
    },
    "((1, 2), (4, 1), 1)": {
        "move_down": 0.0,
        "move_right": 0.0
    },
    "((1, 3), (0, 2), 1)": {
        "move_left": 0.0
    },
    "((0, 3), (1, 2), 1)": {
        "stay": 0.0
    },
    "((0, 3), (2, 2), 1)": {
        "move_down": 0.0,
        "move_right": 0.0
    },
    "((0, 2), (3, 2), 1)": {
        "move_right": 0.0
    },
    "((1, 2), (4, 2), 1)": {
        "move_right": 0.0
    },
    "((4, 3), (3, 3), 0)": {
        "stay": 0.0,
        "move_down": 0.0
    },
    "((1, 2), (0, 1), 0)": {
        "move_left": 0.0252
    },
    "((0, 2), (0, 1), 0)": {
        "move_left": 0.271
    },
    "((1, 0), (0, 0), 0)": {
        "stay": 0.0
    },
    "((4, 2), (1, 1), 0)": {
        "move_up": 0.0,
        "stay": 0.0
    },
    "((4, 2), (0, 0), 0)": {
        "move_down": 0.0
    },
    "((4, 0), (1, 2), 0)": {
        "move_up": 0.0,
        "stay": 0.0,
        "move_left": 0.0
    },
    "((4, 0), (2, 2), 0)": {
        "move_left": 0.0
    },
    "((3, 3), (2, 1), 1)": {
        "move_right": 0.0,
        "move_down": 0.0,
        "move_left": 0.0
    },
    "((4, 3), (3, 1), 1)": {
        "stay": 0.0
    },
    "((4, 3), (4, 1), 1)": {
        "stay": 0.0
    },
    "((3, 2), (3, 1), 1)": {
        "move_left": 0.0,
        "stay": 0.0,
        "move_up": 0.0
    },
    "((2, 2), (2, 1), 0)": {
        "stay": 0.0
    },
    "((2, 1), (4, 1), 0)": {
        "move_right": 0.0
    },
    "((1, 3), (2, 2), 0)": {
        "move_left": 0.0
    },
    "((0, 3), (2, 3), 0)": {
        "move_down": 0.0
    },
    "((0, 2), (1, 3), 0)": {
        "stay": 0.0,
        "move_up": 0.0,
        "move_left": 0.1
    },
    "((0, 2), (1, 2), 0)": {
        "move_right": 0.0
    },
    "((1, 2), (1, 1), 0)": {
        "move_up": 0.0
    },
    "((1, 3), (1, 0), 0)": {
        "move_right": 0.0
    },
    "((2, 3), (1, 1), 0)": {
        "move_down": 0.0
    },
    "((2, 3), (0, 0), 0)": {
        "move_down": 0.0,
        "move_left": 0.0
    },
    "((4, 0), (1, 3), 0)": {
        "move_up": 0.0
    },
    "((4, 3), (3, 3), 1)": {
        "move_left": 0.0
    },
    "((3, 3), (3, 2), 1)": {
        "move_down": 0.0
    },
    "((4, 2), (2, 0), 0)": {
        "move_left": 0.0,
        "stay": 0.0,
        "move_down": 0.0
    },
    "((3, 2), (2, 0), 0)": {
        "move_up": 0.0,
        "stay": 0.0,
        "move_down": 0.0
    },
    "((1, 3), (0, 0), 0)": {
        "move_down": 0.0
    },
    "((1, 2), (0, 3), 0)": {
        "stay": 0.0,
        "move_right": 0.0
    },
    "((2, 3), (1, 3), 0)": {
        "move_left": 0.0,
        "move_down": 0.0
    },
    "((0, 0), (0, 2), 0)": {
        "stay": 0.0,
        "move_up": 0.0
    },
    "((0, 0), (0, 3), 0)": {
        "move_up": 0.0
    },
    "((0, 3), (1, 2), 0)": {
        "stay": 0.0
    },
    "((0, 3), (1, 3), 0)": {
        "stay": 0.0,
        "move_down": 0.0
    },
    "((4, 1), (2, 0), 0)": {
        "move_down": 0.0
    },
    "((4, 0), (2, 1), 0)": {
        "move_up": 0.0
    },
    "((4, 1), (2, 1), 0)": {
        "stay": 0.0
    },
    "((4, 0), (3, 0), 0)": {
        "move_up": 0.0
    },
    "((2, 0), (0, 1), 0)": {
        "stay": 0.0
    },
    "((2, 0), (1, 1), 0)": {
        "move_right": 0.0
    },
    "((3, 0), (2, 1), 0)": {
        "stay": 0.0
    },
    "((4, 0), (3, 1), 0)": {
        "move_up": 0.0
    },
    "((4, 0), (2, 0), 1)": {
        "stay": 0.0
    },
    "((4, 0), (2, 1), 1)": {
        "move_left": 0.0
    },
    "((3, 0), (3, 1), 1)": {
        "move_up": 0.0,
        "move_left": 0.0
    },
    "((3, 0), (4, 1), 1)": {
        "move_right": 0.0
    },
    "((3, 2), (4, 1), 1)": {
        "move_up": 0.0,
        "stay": 0.0
    },
    "((3, 3), (4, 1), 1)": {
        "stay": 0.0
    },
    "((3, 1), (2, 1), 0)": {
        "move_left": 0.0,
        "stay": 0.0,
        "move_down": 0.0
    },
    "((4, 2), (0, 3), 0)": {
        "move_left": 0.0
    },
    "((4, 1), (1, 0), 0)": {
        "stay": 0.0,
        "move_down": 0.0,
        "move_left": 0.0
    },
    "((3, 1), (1, 1), 0)": {
        "move_up": 0.0
    },
    "((3, 1), (2, 0), 0)": {
        "move_up": 0.0
    },
    "((0, 3), (0, 2), 1)": {
        "move_right": 0.0
    },
    "((1, 3), (1, 2), 1)": {
        "move_left": 0.0
    },
    "((2, 3), (4, 2), 1)": {
        "move_left": 0.0
    }
}